bot_kit/__init__.py
bot_kit/__main__.py
bot_kit/common.py
bot_kit/db.py
bot_kit/kit.py
bot_kit-0.1.dist-info/METADATA
bot_kit-0.1.dist-info/WHEEL
bot_kit-0.1.dist-info/top_level.txt
bot_kit-0.1.dist-info/RECORD
