Metadata-Version: 2.1
Name: bot-kit
Version: 0.1
Summary: Telegram bot kit
Home-page: https://github.com/alex19pov31/bot-kit
Author: Alexander Nesterov
Author-email: alex19pov31@gmail.com
License: MIT
Platform: UNKNOWN
Requires-Python: >=3.6
Requires-Dist: aiodns (>=2.0.0)
Requires-Dist: aiogram (>=2.9.2)
Requires-Dist: aiohttp (>=3.6.2)
Requires-Dist: SQLAlchemy (>=1.3.18)
